Metadata-Version: 1.1
Name: django-flat-responsive
Version: 1.1.0
Summary: An extension for Django admin that makes interface mobile friendly.
Home-page: https://github.com/elky/django-flat-responsive
Author: elky
Author-email: mail@elky.me
License: BSD
Download-URL: https://github.com/elky/django-flat-responsive/tarball/1.1.0
Keywords: django,admin,responsive,mobile,interface
Platform: UNKNOWN
Classifier: Development Status :: 5 - Production/Stable
Classifier: Environment :: Web Environment
Classifier: Framework :: Django
Classifier: Intended Audience :: Developers
Classifier: License :: OSI Approved :: BSD License
Classifier: Operating System :: OS Independent
Classifier: Programming Language :: Python
Classifier: Programming Language :: Python :: 2
Classifier: Programming Language :: Python :: 2.7
Classifier: Programming Language :: Python :: 3
Classifier: Programming Language :: Python :: 3.4
Classifier: Programming Language :: Python :: 3.5
